nerve/__init__.py
nerve/__main__.py
nerve/cli/__init__.py
nerve/cli/agents.py
nerve/cli/create.py
nerve/cli/eval.py
nerve/cli/install.py
nerve/cli/namespaces.py
nerve/cli/replay.py
nerve/cli/run.py
nerve/cli/serve.py
nerve/cli/uninstall.py
nerve/cli/utils.py
nerve/cli/utils_test.py
nerve/defaults.py
nerve/generation/__init__.py
nerve/generation/conversation.py
nerve/generation/conversation_test.py
nerve/generation/litellm.py
nerve/generation/ollama.py
nerve/models.py
nerve/models_test.py
nerve/py.typed
nerve/runtime/__init__.py
nerve/runtime/agent.py
nerve/runtime/builtin.py
nerve/runtime/eval.py
nerve/runtime/events.py
nerve/runtime/flow.py
nerve/runtime/flow_test.py
nerve/runtime/logging.py
nerve/runtime/runner.py
nerve/runtime/runner_test.py
nerve/runtime/shell.py
nerve/runtime/state.py
nerve/runtime/state_test.py
nerve/runtime/thread_pool.py
nerve/server/__init__.py
nerve/server/mcp.py
nerve/server/mcp_test.py
nerve/server/rest.py
nerve/tools/__init__.py
nerve/tools/body.j2
nerve/tools/compiler.py
nerve/tools/compiler_test.py
nerve/tools/mcp/__init__.py
nerve/tools/mcp/body.j2
nerve/tools/mcp/client.py
nerve/tools/mcp/compiler.py
nerve/tools/mcp/compiler_test.py
nerve/tools/namespaces/__init__.py
nerve/tools/namespaces/anytool.py
nerve/tools/namespaces/computer.py
nerve/tools/namespaces/filesystem.py
nerve/tools/namespaces/filesystem_test.py
nerve/tools/namespaces/filesystem_w.py
nerve/tools/namespaces/inquire.py
nerve/tools/namespaces/reasoning.py
nerve/tools/namespaces/shell.py
nerve/tools/namespaces/shell_test.py
nerve/tools/namespaces/task.py
nerve/tools/namespaces/time.py
nerve/tools/protocol.py
nerve/tools/protocol_test.py
nerve/tools/utils.py
nerve/tools/utils_test.py
nerve_adk-1.8.0.dist-info/LICENSE
nerve_adk-1.8.0.dist-info/METADATA
nerve_adk-1.8.0.dist-info/WHEEL
nerve_adk-1.8.0.dist-info/entry_points.txt
nerve_adk-1.8.0.dist-info/RECORD
