Metadata-Version: 2.1
Name: nerve-adk
Version: 1.8.0
Summary: The simple agent development kit.
Home-page: https://github.com/evilsocket/nerve
License: GPL-3.0-or-later
Keywords: ai,agent,adk,agent development kit,mcp,model context protocol
Author: evilsocket
Author-email: evilsocket@gmail.com
Requires-Python: >=3.10,<4.0
Classifier: Framework :: Robot Framework
Classifier: License :: OSI Approved :: GNU General Public License v3 or later (GPLv3+)
Classifier: Programming Language :: Python :: 3
Classifier: Programming Language :: Python :: 3.10
Classifier: Programming Language :: Python :: 3.11
Classifier: Programming Language :: Python :: 3.12
Classifier: Topic :: Scientific/Engineering :: Artificial Intelligence
Classifier: Topic :: Software Development :: Build Tools
Classifier: Topic :: Software Development :: Libraries :: Python Modules
Provides-Extra: clipboard
Provides-Extra: computer-use
Requires-Dist: click (>=8.1.8,<9.0.0)
Requires-Dist: fastapi (>=0.115.12,<0.116.0)
Requires-Dist: fastparquet (>=2024.11.0,<2025.0.0)
Requires-Dist: inquirer (>=3.4.0,<4.0.0)
Requires-Dist: jinja2 (>=3.1.5,<4.0.0)
Requires-Dist: litellm (>=1.65.1,<2.0.0)
Requires-Dist: loguru (>=0.7.3,<0.8.0)
Requires-Dist: mcp (>=1.12.2,<2.0.0)
Requires-Dist: natsort (>=8.4.0,<9.0.0)
Requires-Dist: ollama (>=0.4.7,<0.5.0)
Requires-Dist: packaging (>=24.2,<25.0)
Requires-Dist: pillow (>=11.1.0,<12.0.0) ; extra == "computer-use"
Requires-Dist: pyautogui (>=0.9.54,<0.10.0) ; extra == "computer-use"
Requires-Dist: pydantic-yaml (>=1.4.0,<2.0.0)
Requires-Dist: pyperclip (>=1.9.0,<2.0.0) ; extra == "clipboard" or extra == "computer-use"
Requires-Dist: pyscreeze (>=1.0.1,<2.0.0) ; extra == "computer-use"
Requires-Dist: requests (>=2.32.3,<3.0.0)
Requires-Dist: starlette (>=0.46.1,<0.47.0)
Requires-Dist: termcolor (>=2.5.0,<3.0.0)
Requires-Dist: typer (>=0.15.1,<0.16.0)
Requires-Dist: typer-di (>=0.1.3,<0.2.0)
Requires-Dist: types-pyautogui (>=0.9.3.20241230,<0.10.0.0) ; extra == "computer-use"
Requires-Dist: types-pyperclip (>=1.9.0.20250218,<2.0.0.0) ; extra == "clipboard" or extra == "computer-use"
Requires-Dist: types-requests (>=2.32.0.20250328,<3.0.0.0)
Requires-Dist: uuid (>=1.30,<2.0)
Requires-Dist: uvicorn (>=0.34.0,<0.35.0)
Project-URL: Documentation, https://github.com/evilsocket/nerve/docs/index.md
Project-URL: Repository, https://github.com/evilsocket/nerve
